ansys/workbench/core/__init__.py
ansys/workbench/core/example_data.py
ansys/workbench/core/public_api.py
ansys/workbench/core/py.typed
ansys/workbench/core/workbench_client.py
ansys/workbench/core/workbench_launcher.py
ansys_workbench_core-0.10.0.dist-info/licenses/LICENSE
ansys_workbench_core-0.10.0.dist-info/WHEEL
ansys_workbench_core-0.10.0.dist-info/METADATA
ansys_workbench_core-0.10.0.dist-info/RECORD
