Metadata-Version: 2.4
Name: ansys-workbench-core
Version: 0.10.0
Summary: A python wrapper for Ansys Workbench
Author-email: "ANSYS, Inc." <pyansys.core@ansys.com>
Maintainer-email: "ANSYS, Inc." <pyansys.core@ansys.com>
Requires-Python: >=3.10,<4.0
Classifier: Development Status :: 4 - Beta
Classifier: Topic :: Scientific/Engineering
Classifier: License :: OSI Approved :: MIT License
Classifier: Operating System :: OS Independent
Classifier: Programming Language :: Python :: 3.10
Classifier: Programming Language :: Python :: 3.11
Classifier: Programming Language :: Python :: 3.12
Classifier: Programming Language :: Python :: 3.13
License-File: LICENSE
Requires-Dist: ansys_api_workbench>=0.2.0
Requires-Dist: ansys-platform-instancemanagement>=1.0.1
Requires-Dist: ansys-pythonnet>=3.1.0rc1
Requires-Dist: ansys-tools-path>=0.3.1
Requires-Dist: ansys-tools-common>=0.3.0
Requires-Dist: tqdm>=4.65.0
Requires-Dist: WMI>=1.4.9; platform_system=='Windows'
Requires-Dist: ansys-sphinx-theme[autoapi]==1.6.4 ; extra == "doc"
Requires-Dist: numpydoc==1.10.0 ; extra == "doc"
Requires-Dist: Sphinx==8.2.3 ; extra == "doc"
Requires-Dist: sphinx-autodoc-typehints==3.1.0 ; extra == "doc"
Requires-Dist: sphinx-copybutton==0.5.2 ; extra == "doc"
Requires-Dist: jupyter==1.1.1 ; extra == "doc"
Requires-Dist: sphinx-jinja==2.0.2 ; extra == "doc"
Requires-Dist: pytest==9.0.2 ; extra == "tests"
Requires-Dist: pytest-cov==7.0.0 ; extra == "tests"
Requires-Dist: bandit==1.9.2 ; extra == "vulnerabilities"
Requires-Dist: safety==3.7.0 ; extra == "vulnerabilities"
Project-URL: Documentation, https://workbench.docs.pyansys.com
Project-URL: Homepage, https://github.com/ansys/pyworkbench
Project-URL: Source, https://github.com/ansys/pyworkbench
Project-URL: Tracker, https://github.com/ansys/pyworkbench/issues
Provides-Extra: doc
Provides-Extra: tests
Provides-Extra: vulnerabilities
